tls_requests/__init__.py
tls_requests/api.py
tls_requests/client.py
tls_requests/exceptions.py
tls_requests/settings.py
tls_requests/types.py
tls_requests/utils.py
tls_requests/bin/__init__.py
tls_requests/models/__init__.py
tls_requests/models/auth.py
tls_requests/models/cookies.py
tls_requests/models/encoders.py
tls_requests/models/headers.py
tls_requests/models/libraries.py
tls_requests/models/request.py
tls_requests/models/response.py
tls_requests/models/rotators.py
tls_requests/models/status_codes.py
tls_requests/models/tls.py
tls_requests/models/urls.py
wrapper_tls_requests-1.2.3.dist-info/METADATA
wrapper_tls_requests-1.2.3.dist-info/WHEEL
wrapper_tls_requests-1.2.3.dist-info/licenses/LICENSE
wrapper_tls_requests-1.2.3.dist-info/RECORD
