Metadata-Version: 2.4
Name: wrapper-tls-requests
Version: 1.2.3
Summary: A powerful and lightweight Python library for making secure and reliable HTTP/TLS fingerprint requests.
Project-URL: Sponsor, https://github.com/sponsors/thewebscraping
Project-URL: Changelog, https://github.com/thewebscraping/tls-requests/blob/main/CHANGELOG.md
Project-URL: Documentation, https://thewebscraping.github.io/tls-requests/
Project-URL: Source, https://github.com/thewebscraping/tls-requests
Project-URL: Homepage, https://github.com/thewebscraping/tls-requests
Author-email: Tu Pham <thetwofarm@gmail.com>
License-Expression: MIT
License-File: LICENSE
Classifier: Development Status :: 5 - Production/Stable
Classifier: Environment :: Web Environment
Classifier: Intended Audience :: Developers
Classifier: License :: OSI Approved :: MIT License
Classifier: Natural Language :: English
Classifier: Operating System :: OS Independent
Classifier: Programming Language :: Python
Classifier: Programming Language :: Python :: 3
Classifier: Programming Language :: Python :: 3 :: Only
Classifier: Programming Language :: Python :: 3.8
Classifier: Programming Language :: Python :: 3.9
Classifier: Programming Language :: Python :: 3.10
Classifier: Programming Language :: Python :: 3.11
Classifier: Programming Language :: Python :: 3.12
Classifier: Programming Language :: Python :: 3.13
Classifier: Topic :: Internet :: WWW/HTTP
Classifier: Topic :: Software Development :: Libraries
Requires-Python: >=3.8
Requires-Dist: charset-normalizer
Requires-Dist: idna~=3.10
Requires-Dist: orjson
